{
  "city": "yogyakarta",
  "centroid": {
    "lat": -7.7956,
    "lng": 110.3695
  },
  "period": "2014-01-01 to 2023-12-31",
  "source": "Open-Meteo Archive API (ERA5 reanalysis)",
  "generated_at": "2026-02-17T17:14:17.091977",
  "description": "Monthly daily precipitation percentiles (mm). Includes all days (wet+dry).",
  "monthly": {
    "1": {
      "P50": 7.5,
      "P75": 14.07,
      "P90": 21.87,
      "P95": 27.12,
      "P99": 51.47,
      "n_days": 310,
      "mean": 10.37
    },
    "2": {
      "P50": 9.9,
      "P75": 15.57,
      "P90": 24.55,
      "P95": 35.59,
      "P99": 68.78,
      "n_days": 282,
      "mean": 12.66
    },
    "3": {
      "P50": 7.75,
      "P75": 13.53,
      "P90": 19.25,
      "P95": 27.9,
      "P99": 49.39,
      "n_days": 310,
      "mean": 10.23
    },
    "4": {
      "P50": 6.1,
      "P75": 12.03,
      "P90": 18.34,
      "P95": 22.65,
      "P99": 35.14,
      "n_days": 300,
      "mean": 8.6
    },
    "5": {
      "P50": 2.0,
      "P75": 6.2,
      "P90": 12.04,
      "P95": 15.27,
      "P99": 21.28,
      "n_days": 310,
      "mean": 4.17
    },
    "6": {
      "P50": 1.15,
      "P75": 5.53,
      "P90": 11.11,
      "P95": 16.4,
      "P99": 74.24,
      "n_days": 300,
      "mean": 4.76
    },
    "7": {
      "P50": 0.3,
      "P75": 1.4,
      "P90": 4.53,
      "P95": 7.86,
      "P99": 18.13,
      "n_days": 310,
      "mean": 1.61
    },
    "8": {
      "P50": 0.2,
      "P75": 1.2,
      "P90": 3.41,
      "P95": 5.96,
      "P99": 14.91,
      "n_days": 310,
      "mean": 1.26
    },
    "9": {
      "P50": 0.5,
      "P75": 2.1,
      "P90": 9.63,
      "P95": 16.22,
      "P99": 32.01,
      "n_days": 300,
      "mean": 2.95
    },
    "10": {
      "P50": 2.0,
      "P75": 6.2,
      "P90": 16.21,
      "P95": 22.17,
      "P99": 46.44,
      "n_days": 310,
      "mean": 5.42
    },
    "11": {
      "P50": 9.2,
      "P75": 16.12,
      "P90": 24.83,
      "P95": 31.33,
      "P99": 55.85,
      "n_days": 300,
      "mean": 12.52
    },
    "12": {
      "P50": 7.3,
      "P75": 13.4,
      "P90": 22.2,
      "P95": 30.37,
      "P99": 49.11,
      "n_days": 310,
      "mean": 10.22
    }
  }
}